[{"word": "hand", "col": 0, "row": 0, "count": 2}, {"word": "god", "col": 0, "row": 1, "count": 1}, {"word": "simple", "col": 0, "row": 2, "count": 2}, {"word": "flat", "col": 0, "row": 3, "count": 1}, {"word": "world", "col": 0, "row": 4, "count": 1}, {"word": "changing", "col": 0, "row": 5, "count": 1}, {"word": "light", "col": 0, "row": 6, "count": 2}, {"word": "noise", "col": 0, "row": 7, "count": 1}, {"word": "light", "col": 0, "row": 8, "count": 2}, {"word": "dark", "col": 0, "row": 9, "count": 1}, {"word": "dry", "col": 0, "row": 10, "count": 1}, {"word": "damp", "col": 0, "row": 11, "count": 1}, {"word": "chilly", "col": 0, "row": 12, "count": 1}, {"word": "warm", "col": 0, "row": 13, "count": 2}, {"word": "moving", "col": 0, "row": 14, "count": 1}, {"word": "legs", "col": 0, "row": 15, "count": 1}, {"word": "table", "col": 0, "row": 16, "count": 1}, {"word": "chair", "col": 0, "row": 17, "count": 1}, {"word": "rising", "col": 0, "row": 18, "count": 1}, {"word": "falling", "col": 0, "row": 19, "count": 1}, {"word": "grasping", "col": 0, "row": 20, "count": 1}, {"word": "kiss", "col": 0, "row": 21, "count": 1}, {"word": "toy", "col": 0, "row": 22, "count": 1}, {"word": "advancing", "col": 0, "row": 23, "count": 1}, {"word": "boldly", "col": 0, "row": 24, "count": 1}, {"word": "sudden", "col": 0, "row": 25, "count": 1}, {"word": "take", "col": 0, "row": 26, "count": 1}, {"word": "alarm", "col": 0, "row": 27, "count": 1}, {"word": "retreating", "col": 0, "row": 28, "count": 1}, {"word": "corner", "col": 0, "row": 29, "count": 1}, {"word": "arm", "col": 0, "row": 30, "count": 1}, {"word": "knee", "col": 0, "row": 31, "count": 1}, {"word": "eager", "col": 0, "row": 32, "count": 1}, {"word": "reassured", "col": 0, "row": 33, "count": 1}, {"word": "taking", "col": 0, "row": 34, "count": 1}, {"word": "fragrant", "col": 0, "row": 35, "count": 1}, {"word": "brilliance", "col": 0, "row": 36, "count": 1}, {"word": "christmas", "col": 0, "row": 37, "count": 1}, {"word": "tree", "col": 0, "row": 38, "count": 2}, {"word": "pleasure", "col": 0, "row": 39, "count": 1}, {"word": "wind", "col": 0, "row": 40, "count": 1}, {"word": "sunlight", "col": 0, "row": 41, "count": 1}, {"word": "sea", "col": 0, "row": 42, "count": 1}, {"word": "study", "col": 0, "row": 43, "count": 1}, {"word": "sunlit", "col": 0, "row": 44, "count": 1}, {"word": "pattern", "col": 0, "row": 45, "count": 1}, {"word": "running", "col": 0, "row": 46, "count": 1}, {"word": "stag", "col": 0, "row": 47, "count": 1}, {"word": "around", "col": 0, "row": 48, "count": 1}, {"word": "silver", "col": 0, "row": 49, "count": 1}, {"word": "tray", "col": 0, "row": 50, "count": 1}, {"word": "confounds", "col": 0, "row": 51, "count": 1}, {"word": "actual", "col": 0, "row": 52, "count": 1}, {"word": "fanciful", "col": 0, "row": 53, "count": 1}, {"word": "content", "col": 0, "row": 54, "count": 1}, {"word": "king", "col": 1, "row": 0, "count": 1}, {"word": "queens", "col": 1, "row": 1, "count": 1}, {"word": "fairy", "col": 1, "row": 2, "count": 1}, {"word": "servant", "col": 1, "row": 3, "count": 1}, {"word": "heavy", "col": 1, "row": 4, "count": 1}, {"word": "burden", "col": 1, "row": 5, "count": 1}, {"word": "growing", "col": 1, "row": 6, "count": 1}, {"word": "perplexes", "col": 1, "row": 7, "count": 2}, {"word": "offends", "col": 1, "row": 8, "count": 2}, {"word": "day", "col": 1, "row": 9, "count": 2}, {"word": "day", "col": 1, "row": 10, "count": 2}, {"word": "week", "col": 1, "row": 11, "count": 2}, {"word": "week", "col": 1, "row": 12, "count": 2}, {"word": "offends", "col": 1, "row": 13, "count": 2}, {"word": "perplexes", "col": 1, "row": 14, "count": 2}, {"word": "imperative", "col": 1, "row": 15, "count": 1}, {"word": "may", "col": 1, "row": 16, "count": 2}, {"word": "may", "col": 1, "row": 17, "count": 2}, {"word": "desire", "col": 1, "row": 18, "count": 1}, {"word": "pain", "col": 1, "row": 19, "count": 1}, {"word": "living", "col": 1, "row": 20, "count": 2}, {"word": "drug", "col": 1, "row": 21, "count": 1}, {"word": "curl", "col": 1, "row": 22, "count": 1}, {"word": "small", "col": 1, "row": 23, "count": 1}, {"word": "soul", "col": 1, "row": 24, "count": 1}, {"word": "window", "col": 1, "row": 25, "count": 1}, {"word": "behind", "col": 1, "row": 26, "count": 1}, {"word": "britannica", "col": 1, "row": 27, "count": 1}, {"word": "issue", "col": 1, "row": 28, "count": 1}, {"word": "hand", "col": 1, "row": 29, "count": 2}, {"word": "time", "col": 1, "row": 30, "count": 1}, {"word": "simple", "col": 1, "row": 31, "count": 2}, {"word": "irresolute", "col": 1, "row": 32, "count": 1}, {"word": "selfish", "col": 1, "row": 33, "count": 1}, {"word": "misshapen", "col": 1, "row": 34, "count": 1}, {"word": "lame", "col": 1, "row": 35, "count": 1}, {"word": "unable", "col": 1, "row": 36, "count": 1}, {"word": "fare", "col": 1, "row": 37, "count": 1}, {"word": "forward", "col": 1, "row": 38, "count": 1}, {"word": "retreat", "col": 1, "row": 39, "count": 1}, {"word": "fearing", "col": 1, "row": 40, "count": 1}, {"word": "warm", "col": 1, "row": 41, "count": 2}, {"word": "reality", "col": 1, "row": 42, "count": 1}, {"word": "offered", "col": 1, "row": 43, "count": 1}, {"word": "good", "col": 1, "row": 44, "count": 1}, {"word": "denying", "col": 1, "row": 45, "count": 1}, {"word": "importunity", "col": 1, "row": 46, "count": 1}, {"word": "blood", "col": 1, "row": 47, "count": 1}, {"word": "shadow", "col": 1, "row": 48, "count": 2}, {"word": "shadow", "col": 1, "row": 49, "count": 2}, {"word": "spectre", "col": 1, "row": 50, "count": 1}, {"word": "gloom", "col": 1, "row": 51, "count": 1}, {"word": "leaving", "col": 1, "row": 52, "count": 1}, {"word": "disordered", "col": 1, "row": 53, "count": 1}, {"word": "papers", "col": 1, "row": 54, "count": 1}, {"word": "dusty", "col": 2, "row": 0, "count": 1}, {"word": "room", "col": 2, "row": 1, "count": 1}, {"word": "living", "col": 2, "row": 2, "count": 2}, {"word": "first", "col": 2, "row": 3, "count": 1}, {"word": "silence", "col": 2, "row": 4, "count": 1}, {"word": "pray", "col": 2, "row": 5, "count": 3}, {"word": "guiterriez", "col": 2, "row": 6, "count": 1}, {"word": "avid", "col": 2, "row": 7, "count": 1}, {"word": "speed", "col": 2, "row": 8, "count": 1}, {"word": "power", "col": 2, "row": 9, "count": 1}, {"word": "boudin", "col": 2, "row": 10, "count": 1}, {"word": "blown", "col": 2, "row": 11, "count": 1}, {"word": "piece", "col": 2, "row": 12, "count": 1}, {"word": "one", "col": 2, "row": 13, "count": 2}, {"word": "made", "col": 2, "row": 14, "count": 1}, {"word": "great", "col": 2, "row": 15, "count": 1}, {"word": "fortune", "col": 2, "row": 16, "count": 1}, {"word": "one", "col": 2, "row": 17, "count": 2}, {"word": "went", "col": 2, "row": 18, "count": 1}, {"word": "pray", "col": 2, "row": 19, "count": 3}, {"word": "floret", "col": 2, "row": 20, "count": 1}, {"word": "boarhound", "col": 2, "row": 21, "count": 1}, {"word": "slain", "col": 2, "row": 22, "count": 1}, {"word": "yew", "col": 2, "row": 23, "count": 1}, {"word": "tree", "col": 2, "row": 24, "count": 2}, {"word": "pray", "col": 2, "row": 25, "count": 3}, {"word": "us", "col": 2, "row": 26, "count": 1}, {"word": "hour", "col": 2, "row": 27, "count": 1}, {"word": "birth", "col": 2, "row": 28, "count": 1}]